coveragectx/__init__.py
coveragectx/version.py
coveragectx/coverage/__init__.py
coveragectx/coverage/cli.py
coveragectx/coverage/plugin.py
coveragectx/coverage/site/sitecustomize.py
coveragectx/pytest/__init__.py
coveragectx/pytest/plugin.py
pytest_coverage_context-0.7.0.dist-info/LICENSE
pytest_coverage_context-0.7.0.dist-info/METADATA
pytest_coverage_context-0.7.0.dist-info/WHEEL
pytest_coverage_context-0.7.0.dist-info/entry_points.txt
pytest_coverage_context-0.7.0.dist-info/top_level.txt
pytest_coverage_context-0.7.0.dist-info/RECORD
