Metadata-Version: 2.1
Name: pytest-coverage-context
Version: 0.7.0
Summary: Coverage dynamic context support for PyTest, including sub-processes
Home-page: https://github.com/saltstack/pytest-salt-factories
Author: Pedro Algarvio
Author-email: pedro@algarvio.me
License: Apache Software License 2.0
Project-URL: Source, https://github.com/saltstack/pytest-salt-factories
Project-URL: Tracker, https://github.com/saltstack/pytest-salt-factories/issues
Platform: all
Classifier: Programming Language :: Python
Classifier: Programming Language :: Cython
Classifier: Programming Language :: Python :: 3
Classifier: Programming Language :: Python :: 3 :: Only
Classifier: Programming Language :: Python :: 3.5
Classifier: Programming Language :: Python :: 3.6
Classifier: Programming Language :: Python :: 3.7
Classifier: Programming Language :: Python :: 3.8
Classifier: Programming Language :: Python :: 3.9
Classifier: Development Status :: 4 - Beta
Classifier: Intended Audience :: Developers
Classifier: License :: OSI Approved :: Apache Software License
Requires-Python: >=3.5
Requires-Dist: pytest (>=6.1.0)
Requires-Dist: coverage (>=5.3)
Requires-Dist: atomicwrites
